{"cameraMode":{"drawMode":0,"name":"Shaded","section":"Shading Mode"},"sceneLighting":true,"audioPlay":false,"sceneViewState":{"m_AlwaysRefresh":false,"showFog":true,"showSkybox":true,"showFlares":true,"showImageEffects":true,"showParticleSystems":true,"showVisualEffectGraphs":true,"m_FxEnabled":true},"in2DMode":false,"pivot":{"x":-1421.1314697265625,"y":-29.536287307739259,"z":-13.869181632995606},"rotation":{"x":-0.10743404924869538,"y":0.7582845687866211,"z":-0.1262962371110916,"w":-0.6311629414558411},"size":140.5512237548828,"orthographic":false}