{"cameraMode":{"drawMode":0,"name":"Shaded","section":"Shading Mode"},"sceneLighting":false,"audioPlay":false,"sceneViewState":{"m_AlwaysRefresh":false,"showFog":true,"showSkybox":false,"showFlares":true,"showImageEffects":true,"showParticleSystems":true,"showVisualEffectGraphs":true,"m_FxEnabled":true},"in2DMode":false,"pivot":{"x":-99.30010986328125,"y":-30.37360191345215,"z":-66.29549407958985},"rotation":{"x":-0.05850844457745552,"y":0.8488858938217163,"z":-0.09724559634923935,"w":-0.51668781042099},"size":66.32865142822266,"orthographic":false}